MANIFEST.in
NEWS
README.md
dev-requirements.txt
requirements.txt
setup.py
sopel_modules/__init__.py
sopel_modules.bucket.egg-info/PKG-INFO
sopel_modules.bucket.egg-info/SOURCES.txt
sopel_modules.bucket.egg-info/dependency_links.txt
sopel_modules.bucket.egg-info/namespace_packages.txt
sopel_modules.bucket.egg-info/requires.txt
sopel_modules.bucket.egg-info/top_level.txt
sopel_modules/bucket/__init__.py
sopel_modules/bucket/bucket.py