Metadata-Version: 2.1
Name: sopel-modules.bucket
Version: 1.0.3
Summary: A working re-implementation of the xkcd bucket bot for Sopel
Home-page: http://github.com/rustybower/sopel-bucket
Author: Rusty Bower
Author-email: rusty@rustybower.com
License: MIT License
Platform: UNKNOWN
